TMFuncs/__init__.py
TMFuncs/base.py
TMFuncs/batch_kafka.py
TMFuncs/batch_read.py
TMFuncs/generate_dmp_report.py
TMFuncs/op_log.py
TMFuncs/sa_read.py
TMFuncs/send_email.py
TMFuncs/streaming_kafka.py
TMFuncs-0.0.17.dist-info/LICENSE
TMFuncs-0.0.17.dist-info/METADATA
TMFuncs-0.0.17.dist-info/WHEEL
TMFuncs-0.0.17.dist-info/top_level.txt
TMFuncs-0.0.17.dist-info/RECORD
