Metadata-Version: 2.1
Name: TMFuncs
Version: 0.0.17
Summary: Databricks common functions, written by TrueMetrics.
Home-page: https://www.truemetrics.cn/
Author: TSO
Author-email: tlsong@truemetrics.cn
Classifier: Programming Language :: Python :: 3.9
Classifier: License :: OSI Approved :: MIT License
Classifier: Operating System :: OS Independent
License-File: LICENSE
